{
  "main": {
    "id": "efa3d44f18f25528",
    "type": "split",
    "children": [
      {
        "id": "0f67002fc19edbf8",
        "type": "tabs",
        "children": [
          {
            "id": "8228e46f2c941884",
            "type": "leaf",
            "state": {
              "type": "markdown",
              "state": {
                "file": "Módulo 1/0.1 Equipamentos básicos para cultivo indoor.md",
                "mode": "source",
                "source": false
              }
            }
          }
        ]
      }
    ],
    "direction": "vertical"
  },
  "left": {
    "id": "9867026f5c666651",
    "type": "split",
    "children": [
      {
        "id": "e201290510efdd83",
        "type": "tabs",
        "children": [
          {
            "id": "e5ca02e069a37717",
            "type": "leaf",
            "state": {
              "type": "file-explorer",
              "state": {
                "sortOrder": "alphabetical"
              }
            }
          },
          {
            "id": "11737a5d4f80064d",
            "type": "leaf",
            "state": {
              "type": "search",
              "state": {
                "query": "",
                "matchingCase": false,
                "explainSearch": false,
                "collapseAll": false,
                "extraContext": false,
                "sortOrder": "alphabetical"
              }
            }
          },
          {
            "id": "c8de9848201cc8ba",
            "type": "leaf",
            "state": {
              "type": "bookmarks",
              "state": {}
            }
          }
        ]
      }
    ],
    "direction": "horizontal",
    "width": 300
  },
  "right": {
    "id": "b08ec1d93c968ace",
    "type": "split",
    "children": [
      {
        "id": "f9ef15066b4edcf4",
        "type": "tabs",
        "children": [
          {
            "id": "52e1aeb621fa2338",
            "type": "leaf",
            "state": {
              "type": "backlink",
              "state": {
                "file": "Módulo 1/0.1 Equipamentos básicos para cultivo indoor.md",
                "collapseAll": false,
                "extraContext": false,
                "sortOrder": "alphabetical",
                "showSearch": false,
                "searchQuery": "",
                "backlinkCollapsed": false,
                "unlinkedCollapsed": true
              }
            }
          },
          {
            "id": "9bac8af8d5063613",
            "type": "leaf",
            "state": {
              "type": "outgoing-link",
              "state": {
                "file": "Módulo 1/0.1 Equipamentos básicos para cultivo indoor.md",
                "linksCollapsed": false,
                "unlinkedCollapsed": true
              }
            }
          },
          {
            "id": "315f84ddb57d2949",
            "type": "leaf",
            "state": {
              "type": "tag",
              "state": {
                "sortOrder": "frequency",
                "useHierarchy": true
              }
            }
          },
          {
            "id": "3a8b228ed39496f6",
            "type": "leaf",
            "state": {
              "type": "outline",
              "state": {
                "file": "Módulo 1/0.1 Equipamentos básicos para cultivo indoor.md"
              }
            }
          }
        ]
      }
    ],
    "direction": "horizontal",
    "width": 300,
    "collapsed": true
  },
  "left-ribbon": {
    "hiddenItems": {
      "switcher:Abrir a troca rápida": false,
      "graph:Abrir visualização em gráfico": false,
      "canvas:Criar novo canvas": false,
      "daily-notes:Abrir a nota de hoje": false,
      "templates:Inserir modelo": false,
      "command-palette:Abrir paleta de comandos": false
    }
  },
  "active": "8228e46f2c941884",
  "lastOpenFiles": [
    "Módulo 1/0.2 Equipamentos adicionais.md",
    "Sementes/Cannabiorganic.md",
    "Sementes",
    "Módulo 1/0.1 Equipamentos básicos para cultivo indoor.md",
    "Módulo 1",
    "Welcome.md"
  ]
}